{"tags": ["initial_exam", "projection_lat", "side_left"], "description": "", "objects": [{"description": "", "bitmap": null, "tags": [], "classTitle": "text", "points": {"exterior": [[6.0, 89.0], [28.0, 123.0]], "interior": []}}, {"description": "", "bitmap": null, "tags": [], "classTitle": "text", "points": {"exterior": [[0.0, 180.0], [14.0, 193.0]], "interior": []}}, {"description": "", "bitmap": null, "tags": [], "classTitle": "axis", "points": {"exterior": [[116.0, 608.0], [140.0, 10.0]], "interior": []}}], "size": {"height": 609, "width": 298}}