{"tags": [{"name": "ao_classification", "value": "22r-D/2.1"}, "initial_exam", "projection_lat", "side_left"], "description": "", "objects": [{"description": "", "bitmap": null, "tags": [], "classTitle": "text", "points": {"exterior": [[25.09107780456543, 871.1858520507812], [82.17901802062988, 936.8969116210938]], "interior": []}}, {"description": "", "bitmap": null, "tags": [], "classTitle": "fracture", "points": {"exterior": [[162.0, 547.0], [253.0, 635.0]], "interior": []}}, {"description": "", "bitmap": null, "tags": [], "classTitle": "axis", "points": {"exterior": [[209.0, 1048.0], [216.0, 13.0]], "interior": []}}], "size": {"height": 1048, "width": 480}}