{"tags": [{"name": "ao_classification", "value": "23r-M/2.1; 23u-E/7"}, "cast", "projection_lat", "side_right"], "description": "", "objects": [{"description": "", "bitmap": null, "tags": [], "classTitle": "text", "points": {"exterior": [[547.3666172027588, 73.99859237670898], [574.1562099456787, 111.9772834777832]], "interior": []}}, {"description": "", "bitmap": null, "tags": [], "classTitle": "fracture", "points": {"exterior": [[279.67151641845703, 569.5953369140625], [431.0681686401367, 677.3133544921875]], "interior": []}}, {"description": "", "bitmap": null, "tags": [], "classTitle": "axis", "points": {"exterior": [[346.0, 1046.0], [365.0, 25.0]], "interior": []}}], "size": {"height": 1054, "width": 589}}