{"tags": [{"name": "ao_classification", "value": "23r-E/2.1; 23u-E/7"}, "cast", "projection_lat", "side_left"], "description": "", "objects": [{"description": "", "bitmap": null, "tags": [], "classTitle": "text", "points": {"exterior": [[8.0, 877.0], [44.0, 953.0]], "interior": []}}, {"description": "", "bitmap": null, "tags": [], "classTitle": "fracture", "points": {"exterior": [[105.0, 397.0], [304.0, 506.0]], "interior": []}}, {"description": "", "bitmap": null, "tags": [], "classTitle": "axis", "points": {"exterior": [[218.0, 994.0], [211.0, 10.0]], "interior": []}}], "size": {"height": 994, "width": 492}}