{"tags": [{"name": "ao_classification", "value": "23-M/2.1"}, "initial_exam", "projection_ap", "side_right"], "description": "", "objects": [{"description": "", "bitmap": null, "tags": [], "classTitle": "text", "points": {"exterior": [[444.0, 441.0], [496.0, 513.0]], "interior": []}}, {"description": "", "bitmap": null, "tags": [], "classTitle": "fracture", "points": {"exterior": [[178.0, 608.0], [278.0, 667.0]], "interior": []}}, {"description": "", "bitmap": null, "tags": [], "classTitle": "fracture", "points": {"exterior": [[335.0, 606.0], [400.0, 654.0]], "interior": []}}, {"description": "", "bitmap": null, "tags": [], "classTitle": "axis", "points": {"exterior": [[302.0, 928.0], [289.0, 134.0]], "interior": []}}], "size": {"height": 934, "width": 521}}