{"tags": [{"name": "ao_classification", "value": "23r-M/2.1"}, "initial_exam", "projection_lat", "side_left"], "description": "", "objects": [{"description": "", "bitmap": null, "tags": [], "classTitle": "text", "points": {"exterior": [[329.0, 14.0], [388.0, 88.0]], "interior": []}}, {"description": "", "bitmap": null, "tags": [], "classTitle": "fracture", "points": {"exterior": [[141.0, 691.0], [243.0, 761.0]], "interior": []}}, {"description": "", "bitmap": null, "tags": [], "classTitle": "axis", "points": {"exterior": [[152.0, 1252.0], [251.0, 129.0]], "interior": []}}], "size": {"height": 1266, "width": 414}}