{"tags": [{"name": "ao_classification", "value": "23r-M/2.1"}, "initial_exam", "projection_lat", "side_right"], "description": "", "objects": [{"description": "", "bitmap": null, "tags": [], "classTitle": "fracture", "points": {"exterior": [[170.0, 379.0], [289.0, 435.0]], "interior": []}}, {"description": "", "bitmap": null, "tags": [], "classTitle": "text", "points": {"exterior": [[341.0, 188.0], [372.0, 257.0]], "interior": []}}, {"description": "", "bitmap": null, "tags": [], "classTitle": "text", "points": {"exterior": [[335.0, 59.0], [358.0, 91.0]], "interior": []}}, {"description": "", "bitmap": null, "tags": [], "classTitle": "axis", "points": {"exterior": [[251.0, 835.0], [235.0, 23.0]], "interior": []}}], "size": {"height": 854, "width": 372}}