{"tags": [{"name": "ao_classification", "value": "23r-M/3.1; 23u-E/7"}, "cast", "projection_ap", "side_left"], "description": "", "objects": [{"description": "", "bitmap": null, "tags": [], "classTitle": "text", "points": {"exterior": [[80.08653354644775, 82.73351287841797], [96.37415981292725, 112.7120132446289]], "interior": []}}, {"description": "", "bitmap": null, "tags": [], "classTitle": "fracture", "points": {"exterior": [[267.0, 318.0], [411.0, 376.0]], "interior": []}}, {"description": "", "bitmap": null, "tags": [], "classTitle": "text", "points": {"exterior": [[40.873291015625, 153.58056926727295], [73.05032348632812, 173.40075397491455]], "interior": []}}, {"description": "", "bitmap": null, "tags": [], "classTitle": "axis", "points": {"exterior": [[240.0, 775.0], [277.0, 11.0]], "interior": []}}], "size": {"height": 790, "width": 589}}