{"tags": [{"name": "ao_classification", "value": "23-M/3.1; 23u-E/7"}, "cast", "projection_lat", "side_left"], "description": "", "objects": [{"description": "", "bitmap": null, "tags": [], "classTitle": "text", "points": {"exterior": [[7.462028503417969, 209.68431854248047], [56.80664825439453, 280.27017974853516]], "interior": []}}, {"description": "", "bitmap": null, "tags": [], "classTitle": "fracture", "points": {"exterior": [[213.0, 445.0], [350.0, 529.0]], "interior": []}}, {"description": "", "bitmap": null, "tags": [], "classTitle": "axis", "points": {"exterior": [[253.0, 948.0], [337.0, 12.0]], "interior": []}}], "size": {"height": 954, "width": 575}}