{"tags": ["projection_lat", "side_right"], "description": "", "objects": [{"description": "", "bitmap": null, "tags": [], "classTitle": "boneanomaly", "points": {"exterior": [[280.0, 478.0], [410.0, 808.0]], "interior": []}}, {"description": "", "bitmap": null, "tags": [], "classTitle": "text", "points": {"exterior": [[477.0, 300.0], [536.0, 375.0]], "interior": []}}, {"description": "", "bitmap": null, "tags": [], "classTitle": "metal", "points": {"exterior": [[278.0, 559.0], [393.0, 622.0]], "interior": []}}, {"description": "", "bitmap": null, "tags": [], "classTitle": "metal", "points": {"exterior": [[261.0, 497.0], [400.0, 544.0]], "interior": []}}, {"description": "", "bitmap": null, "tags": [], "classTitle": "axis", "points": {"exterior": [[307.0, 1261.0], [298.0, 12.0]], "interior": []}}], "size": {"height": 1268, "width": 536}}