{"tags": [{"name": "ao_classification", "value": "23r-E/2.1"}, "osteopenia", "projection_ap", "side_right"], "description": "", "objects": [{"description": "", "bitmap": null, "tags": [], "classTitle": "fracture", "points": {"exterior": [[145.0, 342.0], [397.0, 448.0]], "interior": []}}, {"description": "", "bitmap": null, "tags": [], "classTitle": "text", "points": {"exterior": [[585.0, 340.0], [626.0, 405.0]], "interior": []}}, {"description": "", "bitmap": null, "tags": [], "classTitle": "axis", "points": {"exterior": [[402.0, 859.0], [353.0, 13.0]], "interior": []}}, {"description": "", "bitmap": null, "tags": [], "classTitle": "periostealreaction", "points": {"exterior": [[358.0, 460.0], [358.0, 469.0], [357.0, 480.0], [357.0, 491.0], [356.0, 505.0], [356.0, 518.0], [353.0, 534.0], [350.0, 544.0], [347.0, 557.0], [347.0, 572.0], [347.0, 582.0], [346.0, 593.0], [346.0, 601.0], [346.0, 608.0], [343.0, 617.0], [342.0, 621.0], [341.0, 598.0], [341.0, 554.0], [341.0, 527.0], [342.0, 511.0], [343.0, 500.0], [344.0, 492.0], [348.0, 481.0], [351.0, 472.0], [353.0, 468.0]], "interior": []}}], "size": {"height": 874, "width": 644}}