{"tags": [{"name": "ao_classification", "value": "23r-M/3.1; 23u-E/7"}, "cast", "projection_ap", "side_left"], "description": "", "objects": [{"description": "", "bitmap": null, "tags": [], "classTitle": "text", "points": {"exterior": [[0.0, 771.0], [48.0, 837.0]], "interior": []}}, {"description": "", "bitmap": null, "tags": [], "classTitle": "fracture", "points": {"exterior": [[210.0, 475.0], [378.0, 566.0]], "interior": []}}, {"description": "", "bitmap": null, "tags": [], "classTitle": "axis", "points": {"exterior": [[243.0, 923.0], [188.0, 22.0]], "interior": []}}, {"description": "", "bitmap": null, "tags": [], "classTitle": "fracture", "points": {"exterior": [[70.0, 409.0], [125.0, 468.0]], "interior": []}}], "size": {"height": 923, "width": 542}}