{"tags": [{"name": "ao_classification", "value": "23r-M/3.1; 23u-E/7"}, "cast", "projection_ap", "side_right"], "description": "", "objects": [{"description": "", "bitmap": null, "tags": [], "classTitle": "text", "points": {"exterior": [[37.13247013092041, 492.9594211578369], [68.07515621185303, 528.3495998382568]], "interior": []}}, {"description": "", "bitmap": null, "tags": [], "classTitle": "fracture", "points": {"exterior": [[185.0, 466.0], [297.0, 553.0]], "interior": []}}, {"description": "", "bitmap": null, "tags": [], "classTitle": "axis", "points": {"exterior": [[347.0, 1111.0], [329.0, 39.0]], "interior": []}}], "size": {"height": 1112, "width": 520}}