{"tags": [{"name": "ao_classification", "value": "23r-M/3.1; 23u-E/7 "}, "initial_exam", "projection_ap", "side_left"], "description": "", "objects": [{"description": "", "bitmap": null, "tags": [], "classTitle": "text", "points": {"exterior": [[489.0, 248.0], [510.0, 282.0]], "interior": []}}, {"description": "", "bitmap": null, "tags": [], "classTitle": "fracture", "points": {"exterior": [[202.0, 375.0], [419.0, 461.0]], "interior": []}}, {"description": "", "bitmap": null, "tags": [], "classTitle": "axis", "points": {"exterior": [[208.0, 973.0], [212.0, 41.0]], "interior": []}}, {"description": "", "bitmap": null, "tags": [], "classTitle": "fracture", "points": {"exterior": [[47.0, 297.0], [119.0, 373.0]], "interior": []}}], "size": {"height": 1001, "width": 570}}