{"tags": [{"name": "ao_classification", "value": "23r-M/2.1"}, "initial_exam", "projection_lat", "side_left"], "description": "", "objects": [{"description": "", "bitmap": null, "tags": [], "classTitle": "text", "points": {"exterior": [[11.0, 64.0], [54.0, 133.0]], "interior": []}}, {"description": "", "bitmap": null, "tags": [], "classTitle": "fracture", "points": {"exterior": [[126.25758743286133, 266.39445877075195], [232.93986129760742, 326.55231857299805]], "interior": []}}, {"description": "", "bitmap": null, "tags": [], "classTitle": "axis", "points": {"exterior": [[149.0, 724.0], [229.0, 14.0]], "interior": []}}], "size": {"height": 732, "width": 340}}