{"tags": [{"name": "ao_classification", "value": "23r-E/2.1"}, "projection_lat", "side_right"], "description": "", "objects": [{"description": "", "bitmap": null, "tags": [], "classTitle": "text", "points": {"exterior": [[345.0, 1015.0], [385.0, 1060.0]], "interior": []}}, {"description": "", "bitmap": null, "tags": [], "classTitle": "text", "points": {"exterior": [[408.0, 1062.0], [436.0, 1127.0]], "interior": []}}, {"description": "", "bitmap": null, "tags": [], "classTitle": "fracture", "points": {"exterior": [[124.0, 538.0], [294.0, 623.0]], "interior": []}}, {"description": "", "bitmap": null, "tags": [], "classTitle": "axis", "points": {"exterior": [[272.0, 1177.0], [233.0, 92.0]], "interior": []}}], "size": {"height": 1194, "width": 436}}