{"tags": [{"name": "ao_classification", "value": "23r-M/2.1; 23u-E/7"}, "initial_exam", "projection_ap", "side_right"], "description": "", "objects": [{"description": "", "bitmap": null, "tags": [], "classTitle": "text", "points": {"exterior": [[155.15692710876465, 1273.135648727417], [191.12871742248535, 1316.497896194458]], "interior": []}}, {"description": "", "bitmap": null, "tags": [], "classTitle": "text", "points": {"exterior": [[592.6118507385254, 1194.985179901123], [627.8500633239746, 1318.157398223877]], "interior": []}}, {"description": "", "bitmap": null, "tags": [], "classTitle": "fracture", "points": {"exterior": [[512.0, 575.0], [575.0, 636.0]], "interior": []}}, {"description": "", "bitmap": null, "tags": [], "classTitle": "fracture", "points": {"exterior": [[227.0, 630.0], [432.0, 687.0]], "interior": []}}, {"description": "", "bitmap": null, "tags": [], "classTitle": "axis", "points": {"exterior": [[424.0, 1394.0], [418.0, 179.0]], "interior": []}}], "size": {"height": 1394, "width": 754}}