{"tags": [{"name": "ao_classification", "value": "72B(c)"}, "diagnosis_uncertain", "initial_exam", "projection_ap", "side_right"], "description": "", "objects": [{"description": "", "bitmap": null, "tags": [], "classTitle": "text", "points": {"exterior": [[523.0, 896.0], [592.0, 1023.0]], "interior": []}}, {"description": "", "bitmap": null, "tags": [], "classTitle": "axis", "points": {"exterior": [[343.0, 1470.0], [356.0, 158.0]], "interior": []}}, {"description": "", "bitmap": null, "tags": [], "classTitle": "fracture", "points": {"exterior": [[169.0, 503.0], [200.0, 565.0]], "interior": []}}], "size": {"height": 1475, "width": 592}}