{"tags": [{"name": "ao_classification", "value": "23r-M/3.1"}, "osteopenia", "projection_lat", "side_right"], "description": "", "objects": [{"description": "", "bitmap": null, "tags": [], "classTitle": "text", "points": {"exterior": [[1.0, 503.0], [28.0, 523.0]], "interior": []}}, {"description": "", "bitmap": null, "tags": [], "classTitle": "text", "points": {"exterior": [[40.0, 51.0], [65.0, 88.0]], "interior": []}}, {"description": "", "bitmap": null, "tags": [], "classTitle": "fracture", "points": {"exterior": [[118.0, 485.0], [260.0, 577.0]], "interior": []}}, {"description": "", "bitmap": null, "tags": [], "classTitle": "axis", "points": {"exterior": [[213.0, 1087.0], [214.0, 42.0]], "interior": []}}, {"description": "", "bitmap": null, "tags": [], "classTitle": "periostealreaction", "points": {"exterior": [[130.0, 540.0], [132.0, 557.0], [142.0, 581.0], [147.0, 603.0], [152.0, 636.0], [157.0, 687.0], [164.0, 715.0], [162.0, 589.0], [154.0, 563.0], [146.0, 554.0]], "interior": []}}], "size": {"height": 1116, "width": 438}}