{"tags": [{"name": "ao_classification", "value": "23r-M/2.1"}, "diagnosis_uncertain", "initial_exam", "projection_lat", "side_right"], "description": "", "objects": [{"description": "", "bitmap": null, "tags": [], "classTitle": "text", "points": {"exterior": [[109.0, 903.0], [138.0, 939.0]], "interior": []}}, {"description": "", "bitmap": null, "tags": [], "classTitle": "axis", "points": {"exterior": [[363.0, 999.0], [315.0, 89.0]], "interior": []}}, {"description": "", "bitmap": null, "tags": [], "classTitle": "fracture", "points": {"exterior": [[272.0, 471.0], [399.0, 555.0]], "interior": []}}], "size": {"height": 1023, "width": 594}}