{"tags": [{"name": "ao_classification", "value": "23r-M/2.1; 23u-E7"}, "cast", "projection_ap", "side_left"], "description": "", "objects": [{"description": "", "bitmap": null, "tags": [], "classTitle": "text", "points": {"exterior": [[20.0, 868.0], [45.0, 892.0]], "interior": []}}, {"description": "", "bitmap": null, "tags": [], "classTitle": "text", "points": {"exterior": [[46.0, 482.0], [76.0, 529.0]], "interior": []}}, {"description": "", "bitmap": null, "tags": [], "classTitle": "fracture", "points": {"exterior": [[162.0, 583.0], [224.0, 643.0]], "interior": []}}, {"description": "", "bitmap": null, "tags": [], "classTitle": "fracture", "points": {"exterior": [[316.0, 694.0], [488.0, 761.0]], "interior": []}}, {"description": "", "bitmap": null, "tags": [], "classTitle": "axis", "points": {"exterior": [[272.0, 1241.0], [334.0, 39.0]], "interior": []}}], "size": {"height": 1274, "width": 739}}