{"tags": [{"name": "ao_classification", "value": "23-M/2.1"}, "initial_exam", "projection_ap", "side_left"], "description": "", "objects": [{"description": "", "bitmap": null, "tags": [], "classTitle": "text", "points": {"exterior": [[43.0, 551.0], [91.0, 628.0]], "interior": []}}, {"description": "", "bitmap": null, "tags": [], "classTitle": "fracture", "points": {"exterior": [[152.0, 702.0], [258.0, 771.0]], "interior": []}}, {"description": "", "bitmap": null, "tags": [], "classTitle": "fracture", "points": {"exterior": [[313.0, 839.0], [438.0, 920.0]], "interior": []}}, {"description": "", "bitmap": null, "tags": [], "classTitle": "axis", "points": {"exterior": [[185.0, 1334.0], [411.0, 71.0]], "interior": []}}], "size": {"height": 1364, "width": 680}}