{"tags": [{"name": "ao_classification", "value": "23r-M/2.1; 23u-E/7"}, "initial_exam", "projection_lat", "side_left"], "description": "", "objects": [{"description": "", "bitmap": null, "tags": [], "classTitle": "fracture", "points": {"exterior": [[204.0, 681.0], [318.0, 747.0]], "interior": []}}, {"description": "", "bitmap": null, "tags": [], "classTitle": "text", "points": {"exterior": [[28.0, 308.0], [76.0, 380.0]], "interior": []}}, {"description": "", "bitmap": null, "tags": [], "classTitle": "axis", "points": {"exterior": [[266.0, 1155.0], [255.0, 71.0]], "interior": []}}], "size": {"height": 1206, "width": 591}}