{"tags": [{"name": "ao_classification", "value": "23r-M/2.1"}, "initial_exam", "projection_lat", "side_left"], "description": "", "objects": [{"description": "", "bitmap": null, "tags": [], "classTitle": "text", "points": {"exterior": [[256.0, 889.0], [274.0, 918.0]], "interior": []}}, {"description": "", "bitmap": null, "tags": [], "classTitle": "text", "points": {"exterior": [[16.0, 372.0], [26.0, 377.0]], "interior": []}}, {"description": "", "bitmap": null, "tags": [], "classTitle": "fracture", "points": {"exterior": [[112.0, 461.0], [239.0, 523.0]], "interior": []}}, {"description": "", "bitmap": null, "tags": [], "classTitle": "axis", "points": {"exterior": [[162.0, 981.0], [150.0, 40.0]], "interior": []}}], "size": {"height": 1006, "width": 450}}