{"tags": [{"name": "ao_classification", "value": "23r-E/2.1; 23u-E/7"}, "cast", "osteopenia", "projection_ap", "side_right"], "description": "", "objects": [{"description": "", "bitmap": null, "tags": [], "classTitle": "axis", "points": {"exterior": [[363.0, 1215.0], [358.0, 40.0]], "interior": []}}, {"description": "", "bitmap": null, "tags": [], "classTitle": "fracture", "points": {"exterior": [[456.0, 570.0], [520.0, 639.0]], "interior": []}}, {"description": "", "bitmap": null, "tags": [], "classTitle": "fracture", "points": {"exterior": [[140.0, 624.0], [372.0, 748.0]], "interior": []}}, {"description": "", "bitmap": null, "tags": [], "classTitle": "text", "points": {"exterior": [[591.0, 1112.0], [626.0, 1153.0]], "interior": []}}], "size": {"height": 1229, "width": 640}}