{"tags": [{"name": "ao_classification", "value": "23r-E/2.1; 23u-M/2.1"}, "cast", "projection_ap", "side_left"], "description": "", "objects": [{"description": "", "bitmap": null, "tags": [], "classTitle": "text", "points": {"exterior": [[119.08507537841797, 557.0648250579834], [140.6408462524414, 596.2415714263916]], "interior": []}}, {"description": "", "bitmap": null, "tags": [], "classTitle": "text", "points": {"exterior": [[154.12171936035156, 817.2487106323242], [191.5395965576172, 879.5503616333008]], "interior": []}}, {"description": "", "bitmap": null, "tags": [], "classTitle": "fracture", "points": {"exterior": [[449.6698226928711, 625.3000564575195], [601.6218032836914, 697.613883972168]], "interior": []}}, {"description": "", "bitmap": null, "tags": [], "classTitle": "axis", "points": {"exterior": [[486.0, 1083.0], [371.0, 40.0]], "interior": []}}], "size": {"height": 1120, "width": 920}}