{"tags": [{"name": "ao_classification", "value": "23r-E/2.1; 23u-E/7"}, "cast", "projection_lat", "side_left"], "description": "", "objects": [{"description": "", "bitmap": null, "tags": [], "classTitle": "text", "points": {"exterior": [[179.0, 108.0], [242.0, 213.0]], "interior": []}}, {"description": "", "bitmap": null, "tags": [], "classTitle": "fracture", "points": {"exterior": [[429.0, 640.0], [653.0, 750.0]], "interior": []}}, {"description": "", "bitmap": null, "tags": [], "classTitle": "axis", "points": {"exterior": [[438.0, 1362.0], [581.0, 87.0]], "interior": []}}], "size": {"height": 1426, "width": 1040}}