{"tags": [{"name": "ao_classification", "value": "23r-M/3.1"}, "initial_exam", "projection_lat", "side_left"], "description": "", "objects": [{"description": "", "bitmap": null, "tags": [], "classTitle": "text", "points": {"exterior": [[25.0, 493.0], [81.0, 560.0]], "interior": []}}, {"description": "", "bitmap": null, "tags": [], "classTitle": "fracture", "points": {"exterior": [[193.0, 304.0], [288.0, 376.0]], "interior": []}}, {"description": "", "bitmap": null, "tags": [], "classTitle": "axis", "points": {"exterior": [[250.0, 1175.0], [247.0, 67.0]], "interior": []}}], "size": {"height": 1210, "width": 528}}