{"tags": [{"name": "ao_classification", "value": "23r-M/3.1"}, "projection_oblique", "side_right"], "description": "", "objects": [{"description": "", "bitmap": null, "tags": [], "classTitle": "text", "points": {"exterior": [[439.0, 150.0], [499.0, 228.0]], "interior": []}}, {"description": "", "bitmap": null, "tags": [], "classTitle": "fracture", "points": {"exterior": [[233.0, 328.0], [303.0, 396.0]], "interior": []}}, {"description": "", "bitmap": null, "tags": [], "classTitle": "periostealreaction", "points": {"exterior": [[350.0, 673.0], [341.0, 624.0], [319.0, 531.0], [310.0, 460.0], [309.0, 428.0], [310.0, 403.0], [311.0, 372.0], [308.0, 344.0], [302.0, 326.0], [292.0, 353.0], [282.0, 366.0], [298.0, 496.0], [331.0, 623.0], [342.0, 671.0]], "interior": []}}, {"description": "", "bitmap": null, "tags": [], "classTitle": "axis", "points": {"exterior": [[364.0, 689.0], [266.0, 58.0]], "interior": []}}], "size": {"height": 722, "width": 541}}