{"tags": [{"name": "ao_classification", "value": "23r-M/2.1; 23u-E/7"}, "projection_ap", "side_left"], "description": "", "objects": [{"description": "", "bitmap": null, "tags": [], "classTitle": "text", "points": {"exterior": [[11.0, 795.0], [82.0, 912.0]], "interior": []}}, {"description": "", "bitmap": null, "tags": [], "classTitle": "fracture", "points": {"exterior": [[69.0, 429.0], [139.0, 489.0]], "interior": []}}, {"description": "", "bitmap": null, "tags": [], "classTitle": "axis", "points": {"exterior": [[181.0, 933.0], [223.0, 38.0]], "interior": []}}, {"description": "", "bitmap": null, "tags": [], "classTitle": "fracture", "points": {"exterior": [[226.0, 652.0], [390.0, 723.0]], "interior": []}}], "size": {"height": 942, "width": 529}}