{"tags": [{"name": "ao_classification", "value": "23r-M/2.1"}, "initial_exam", "projection_lat", "side_left"], "description": "", "objects": [{"description": "", "bitmap": null, "tags": [], "classTitle": "fracture", "points": {"exterior": [[132.0, 449.0], [238.0, 518.0]], "interior": []}}, {"description": "", "bitmap": null, "tags": [], "classTitle": "text", "points": {"exterior": [[21.0, 712.0], [43.0, 744.0]], "interior": []}}, {"description": "", "bitmap": null, "tags": [], "classTitle": "axis", "points": {"exterior": [[190.0, 799.0], [197.0, 33.0]], "interior": []}}], "size": {"height": 802, "width": 393}}