{"tags": [{"name": "ao_classification", "value": "23r-M/3.1; 23u-M/2.1"}, "cast", "projection_lat", "side_left"], "description": "", "objects": [{"description": "", "bitmap": null, "tags": [], "classTitle": "fracture", "points": {"exterior": [[243.0, 554.0], [345.0, 657.0]], "interior": []}}, {"description": "", "bitmap": null, "tags": [], "classTitle": "text", "points": {"exterior": [[95.0, 147.0], [113.0, 178.0]], "interior": []}}, {"description": "", "bitmap": null, "tags": [], "classTitle": "text", "points": {"exterior": [[47.0, 188.0], [72.0, 199.0]], "interior": []}}, {"description": "", "bitmap": null, "tags": [], "classTitle": "axis", "points": {"exterior": [[253.0, 1067.0], [339.0, 53.0]], "interior": []}}], "size": {"height": 1112, "width": 562}}