{"tags": [{"name": "ao_classification", "value": "23-M/3.1"}, "cast", "projection_ap", "side_right"], "description": "", "objects": [{"description": "", "bitmap": null, "tags": [], "classTitle": "fracture", "points": {"exterior": [[227.0, 438.0], [320.0, 507.0]], "interior": []}}, {"description": "", "bitmap": null, "tags": [], "classTitle": "text", "points": {"exterior": [[561.0, 466.0], [579.0, 488.0]], "interior": []}}, {"description": "", "bitmap": null, "tags": [], "classTitle": "axis", "points": {"exterior": [[318.0, 584.0], [415.0, 120.0]], "interior": []}}, {"description": "", "bitmap": null, "tags": [], "classTitle": "fracture", "points": {"exterior": [[367.0, 463.0], [430.0, 528.0]], "interior": []}}], "size": {"height": 632, "width": 658}}