{"tags": [{"name": "ao_classification", "value": "23r-M/3.1; 23u-M/2.1"}, "cast", "projection_ap", "side_left"], "description": "", "objects": [{"description": "", "bitmap": null, "tags": [], "classTitle": "text", "points": {"exterior": [[8.0, 1006.0], [69.0, 1073.0]], "interior": []}}, {"description": "", "bitmap": null, "tags": [], "classTitle": "fracture", "points": {"exterior": [[305.8644714355469, 511.383544921875], [458.2383117675781, 595.6087646484375]], "interior": []}}, {"description": "", "bitmap": null, "tags": [], "classTitle": "axis", "points": {"exterior": [[279.0, 1126.0], [299.0, 26.0]], "interior": []}}, {"description": "", "bitmap": null, "tags": [], "classTitle": "boneanomaly", "points": {"exterior": [[132.0, 272.0], [313.0, 510.0]], "interior": []}}], "size": {"height": 1147, "width": 606}}