{"tags": [{"name": "ao_classification", "value": "23r-M/3.1"}, "osteopenia", "projection_ap", "side_left"], "description": "", "objects": [{"description": "", "bitmap": null, "tags": [], "classTitle": "text", "points": {"exterior": [[64.54875659942627, 989.7523097991943], [88.61448192596436, 1035.2271823883057]], "interior": []}}, {"description": "", "bitmap": null, "tags": [], "classTitle": "fracture", "points": {"exterior": [[298.1021194458008, 529.2094879150391], [434.26683807373047, 616.3554534912109]], "interior": []}}, {"description": "", "bitmap": null, "tags": [], "classTitle": "text", "points": {"exterior": [[1.7089710235595703, 1068.1196975708008], [41.99391746520996, 1165.4430465698242]], "interior": []}}, {"description": "", "bitmap": null, "tags": [], "classTitle": "axis", "points": {"exterior": [[167.0, 1166.0], [346.0, 32.0]], "interior": []}}, {"description": "", "bitmap": null, "tags": [], "classTitle": "periostealreaction", "points": {"exterior": [[317.0, 471.0], [318.0, 492.0], [315.0, 521.0], [312.0, 536.0], [310.0, 559.0], [308.0, 579.0], [308.0, 605.0], [303.0, 638.0], [294.0, 706.0], [309.0, 659.0], [319.0, 609.0], [319.0, 583.0], [318.0, 567.0], [326.0, 565.0], [332.0, 559.0], [330.0, 548.0], [322.0, 541.0], [324.0, 527.0], [323.0, 494.0], [320.0, 476.0]], "interior": []}}], "size": {"height": 1216, "width": 569}}