{"tags": [{"name": "ao_classification", "value": "23r-M/2.1"}, "diagnosis_uncertain", "initial_exam", "projection_lat", "side_left"], "description": "", "objects": [{"description": "", "bitmap": null, "tags": [], "classTitle": "text", "points": {"exterior": [[0.0, 213.0], [44.0, 278.0]], "interior": []}}, {"description": "", "bitmap": null, "tags": [], "classTitle": "axis", "points": {"exterior": [[183.0, 1304.0], [181.0, 28.0]], "interior": []}}, {"description": "", "bitmap": null, "tags": [], "classTitle": "fracture", "points": {"exterior": [[146.0, 414.0], [234.0, 484.0]], "interior": []}}], "size": {"height": 1304, "width": 391}}