{"tags": [{"name": "ao_classification", "value": "23r-M/3.1"}, "projection_ap", "side_left"], "description": "", "objects": [{"description": "", "bitmap": null, "tags": [], "classTitle": "text", "points": {"exterior": [[456.0, 932.0], [482.0, 973.0]], "interior": []}}, {"description": "", "bitmap": null, "tags": [], "classTitle": "fracture", "points": {"exterior": [[309.0, 522.0], [479.0, 593.0]], "interior": []}}, {"description": "", "bitmap": null, "tags": [], "classTitle": "axis", "points": {"exterior": [[311.0, 1021.0], [329.0, 55.0]], "interior": []}}, {"description": "", "bitmap": null, "tags": [], "classTitle": "periostealreaction", "points": {"exterior": [[421.0, 808.0], [429.0, 724.0], [440.0, 674.0], [461.0, 601.0], [470.0, 575.0], [474.0, 549.0], [460.0, 568.0], [445.0, 606.0], [429.0, 659.0], [422.0, 732.0]], "interior": []}}], "size": {"height": 1064, "width": 743}}