{"tags": [{"name": "ao_classification", "value": "23-M/2.1"}, "osteopenia", "projection_lat", "side_left"], "description": "", "objects": [{"description": "", "bitmap": null, "tags": [], "classTitle": "fracture", "points": {"exterior": [[144.0, 533.0], [242.0, 599.0]], "interior": []}}, {"description": "", "bitmap": null, "tags": [], "classTitle": "periostealreaction", "points": {"exterior": [[151.0, 551.0], [147.0, 523.0], [125.0, 491.0], [143.0, 561.0], [149.0, 829.0], [167.0, 629.0], [171.0, 560.0], [159.0, 557.0]], "interior": []}}, {"description": "", "bitmap": null, "tags": [], "classTitle": "text", "points": {"exterior": [[54.0, 95.0], [78.0, 129.0]], "interior": []}}, {"description": "", "bitmap": null, "tags": [], "classTitle": "axis", "points": {"exterior": [[195.0, 1068.0], [228.0, 1.0]], "interior": []}}], "size": {"height": 1074, "width": 530}}