{"tags": [{"name": "ao_classification", "value": "23-M/2.1"}, "cast", "projection_lat", "side_right"], "description": "", "objects": [{"description": "", "bitmap": null, "tags": [], "classTitle": "text", "points": {"exterior": [[604.0, 385.0], [657.0, 448.0]], "interior": []}}, {"description": "", "bitmap": null, "tags": [], "classTitle": "fracture", "points": {"exterior": [[352.0, 768.0], [468.0, 878.0]], "interior": []}}, {"description": "", "bitmap": null, "tags": [], "classTitle": "axis", "points": {"exterior": [[422.0, 1175.0], [389.0, 188.0]], "interior": []}}], "size": {"height": 1224, "width": 745}}