{"tags": [{"name": "ao_classification", "value": "23-M/3.1"}, "cast", "projection_lat", "side_left"], "description": "", "objects": [{"description": "", "bitmap": null, "tags": [], "classTitle": "text", "points": {"exterior": [[80.13037014007568, 1190.5657043457031], [107.12643527984619, 1241.3888854980469]], "interior": []}}, {"description": "", "bitmap": null, "tags": [], "classTitle": "fracture", "points": {"exterior": [[153.20115661621094, 693.5213432312012], [298.50389099121094, 818.9837837219238]], "interior": []}}, {"description": "", "bitmap": null, "tags": [], "classTitle": "fracture", "points": {"exterior": [[229.0, 683.0], [324.0, 767.0]], "interior": []}}, {"description": "", "bitmap": null, "tags": [], "classTitle": "axis", "points": {"exterior": [[229.0, 1280.0], [267.0, 35.0]], "interior": []}}], "size": {"height": 1292, "width": 493}}