{"tags": [{"name": "ao_classification", "value": "23-M/3.1"}, "cast", "projection_ap", "side_right"], "description": "", "objects": [{"description": "", "bitmap": null, "tags": [], "classTitle": "text", "points": {"exterior": [[561.0, 73.0], [602.0, 115.0]], "interior": []}}, {"description": "", "bitmap": null, "tags": [], "classTitle": "fracture", "points": {"exterior": [[351.0, 489.0], [456.0, 537.0]], "interior": []}}, {"description": "", "bitmap": null, "tags": [], "classTitle": "fracture", "points": {"exterior": [[189.0, 566.0], [295.0, 634.0]], "interior": []}}, {"description": "", "bitmap": null, "tags": [], "classTitle": "axis", "points": {"exterior": [[298.0, 1063.0], [357.0, 41.0]], "interior": []}}], "size": {"height": 1075, "width": 672}}