{"tags": ["initial_exam", "projection_ap", "side_right"], "description": "", "objects": [{"description": "", "bitmap": null, "tags": [], "classTitle": "text", "points": {"exterior": [[605.7506656646729, 408.6109733581543], [639.7382259368896, 476.52946853637695]], "interior": []}}, {"description": "", "bitmap": null, "tags": [], "classTitle": "text", "points": {"exterior": [[578.9637985229492, 64.64754295349121], [599.1644973754883, 92.10616493225098]], "interior": []}}, {"description": "", "bitmap": null, "tags": [], "classTitle": "axis", "points": {"exterior": [[372.0, 740.0], [380.0, 39.0]], "interior": []}}], "size": {"height": 746, "width": 654}}