{"tags": [{"name": "ao_classification", "value": "23r-M/3.1; 23u-M/2.1"}, "osteopenia", "projection_ap", "side_left"], "description": "", "objects": [{"description": "", "bitmap": null, "tags": [], "classTitle": "text", "points": {"exterior": [[9.757161140441895, 235.87332916259766], [29.698351860046387, 271.08019256591797]], "interior": []}}, {"description": "", "bitmap": null, "tags": [], "classTitle": "fracture", "points": {"exterior": [[216.0, 505.0], [345.0, 628.0]], "interior": []}}, {"description": "", "bitmap": null, "tags": [], "classTitle": "text", "points": {"exterior": [[4.707255840301514, 392.00858211517334], [15.036964893341064, 404.3900384902954]], "interior": []}}, {"description": "", "bitmap": null, "tags": [], "classTitle": "axis", "points": {"exterior": [[205.0, 972.0], [210.0, 3.0]], "interior": []}}, {"description": "", "bitmap": null, "tags": [], "classTitle": "periostealreaction", "points": {"exterior": [[328.0, 733.0], [333.0, 678.0], [337.0, 617.0], [343.0, 595.0], [342.0, 574.0], [340.0, 526.0], [332.0, 577.0], [330.0, 596.0], [326.0, 608.0], [324.0, 647.0], [324.0, 702.0], [325.0, 723.0]], "interior": []}}, {"description": "", "bitmap": null, "tags": [], "classTitle": "periostealreaction", "points": {"exterior": [[220.0, 503.0], [220.0, 529.0], [216.0, 551.0], [219.0, 569.0], [227.0, 596.0], [234.0, 639.0], [243.0, 701.0], [246.0, 651.0], [239.0, 612.0], [232.0, 574.0], [228.0, 539.0], [228.0, 516.0], [221.0, 486.0]], "interior": []}}, {"description": "", "bitmap": null, "tags": [], "classTitle": "fracture", "points": {"exterior": [[84.0, 417.0], [172.0, 486.0]], "interior": []}}], "size": {"height": 978, "width": 571}}