{"tags": [{"name": "ao_classification", "value": "23r-M/3.1; 23u-E/7"}, "cast", "projection_lat", "side_right"], "description": "", "objects": [{"description": "", "bitmap": null, "tags": [], "classTitle": "text", "points": {"exterior": [[25.0, 622.0], [110.0, 735.0]], "interior": []}}, {"description": "", "bitmap": null, "tags": [], "classTitle": "fracture", "points": {"exterior": [[296.0, 230.0], [461.0, 328.0]], "interior": []}}, {"description": "", "bitmap": null, "tags": [], "classTitle": "axis", "points": {"exterior": [[327.0, 837.0], [381.0, 35.0]], "interior": []}}], "size": {"height": 854, "width": 595}}