{"tags": [{"name": "ao_classification", "value": "23r-M/3.1; 23u-E/7"}, "initial_exam", "projection_ap", "side_right"], "description": "", "objects": [{"description": "", "bitmap": null, "tags": [], "classTitle": "text", "points": {"exterior": [[429.0, 402.0], [480.0, 473.0]], "interior": []}}, {"description": "", "bitmap": null, "tags": [], "classTitle": "fracture", "points": {"exterior": [[139.0, 472.0], [295.0, 558.0]], "interior": []}}, {"description": "", "bitmap": null, "tags": [], "classTitle": "axis", "points": {"exterior": [[283.0, 900.0], [287.0, 28.0]], "interior": []}}, {"description": "", "bitmap": null, "tags": [], "classTitle": "fracture", "points": {"exterior": [[355.0, 432.0], [400.0, 481.0]], "interior": []}}], "size": {"height": 906, "width": 480}}