{"tags": [{"name": "ao_classification", "value": "23r-M/2.1"}, "initial_exam", "projection_lat", "side_left"], "description": "", "objects": [{"description": "", "bitmap": null, "tags": [], "classTitle": "text", "points": {"exterior": [[36.0, 890.0], [59.0, 923.0]], "interior": []}}, {"description": "", "bitmap": null, "tags": [], "classTitle": "axis", "points": {"exterior": [[139.0, 994.0], [186.0, 27.0]], "interior": []}}, {"description": "", "bitmap": null, "tags": [], "classTitle": "fracture", "points": {"exterior": [[82.0, 541.0], [228.0, 614.0]], "interior": []}}], "size": {"height": 1000, "width": 403}}