{"tags": [{"name": "ao_classification", "value": "23r-M/3.1"}, "initial_exam", "projection_ap", "side_left"], "description": "", "objects": [{"description": "", "bitmap": null, "tags": [], "classTitle": "text", "points": {"exterior": [[122.0, 678.0], [144.0, 712.0]], "interior": []}}, {"description": "", "bitmap": null, "tags": [], "classTitle": "fracture", "points": {"exterior": [[268.0, 521.0], [415.0, 608.0]], "interior": []}}, {"description": "", "bitmap": null, "tags": [], "classTitle": "axis", "points": {"exterior": [[264.0, 955.0], [275.0, 68.0]], "interior": []}}], "size": {"height": 982, "width": 662}}