{"tags": [{"name": "ao_classification", "value": "23r-E/2.1; 23u-E/7"}, "projection_lat", "side_right"], "description": "", "objects": [{"description": "", "bitmap": null, "tags": [], "classTitle": "text", "points": {"exterior": [[152.6364574432373, 642.4751100540161], [175.3546314239502, 668.8946409225464]], "interior": []}}, {"description": "", "bitmap": null, "tags": [], "classTitle": "fracture", "points": {"exterior": [[210.0, 379.0], [386.0, 504.0]], "interior": []}}, {"description": "", "bitmap": null, "tags": [], "classTitle": "axis", "points": {"exterior": [[289.0, 753.0], [298.0, 15.0]], "interior": []}}], "size": {"height": 761, "width": 528}}