{"tags": [{"name": "ao_classification", "value": "23r-E/2.1; 23u-E/7"}, "initial_exam", "projection_lat", "side_right"], "description": "", "objects": [{"description": "", "bitmap": null, "tags": [], "classTitle": "fracture", "points": {"exterior": [[161.0, 356.0], [364.0, 508.0]], "interior": []}}, {"description": "", "bitmap": null, "tags": [], "classTitle": "text", "points": {"exterior": [[410.0, 548.0], [462.0, 618.0]], "interior": []}}, {"description": "", "bitmap": null, "tags": [], "classTitle": "axis", "points": {"exterior": [[231.0, 838.0], [308.0, 35.0]], "interior": []}}, {"description": "", "bitmap": null, "tags": [], "classTitle": "softtissue", "points": {"exterior": [[106.0, 331.0], [206.0, 623.0]], "interior": []}}, {"description": "", "bitmap": null, "tags": [], "classTitle": "softtissue", "points": {"exterior": [[336.0, 283.0], [417.0, 466.0]], "interior": []}}], "size": {"height": 870, "width": 490}}