{"tags": [{"name": "ao_classification", "value": "23r-M/3.1; 23u-M/2."}, "cast", "projection_ap", "side_left"], "description": "", "objects": [{"description": "", "bitmap": null, "tags": [], "classTitle": "fracture", "points": {"exterior": [[255.0, 482.0], [381.0, 559.0]], "interior": []}}, {"description": "", "bitmap": null, "tags": [], "classTitle": "text", "points": {"exterior": [[3.0, 51.0], [22.0, 80.0]], "interior": []}}, {"description": "", "bitmap": null, "tags": [], "classTitle": "axis", "points": {"exterior": [[250.0, 769.0], [233.0, 48.0]], "interior": []}}, {"description": "", "bitmap": null, "tags": [], "classTitle": "periostealreaction", "points": {"exterior": [[254.0, 498.0], [253.0, 514.0], [253.0, 532.0], [260.0, 551.0], [269.0, 569.0], [282.0, 615.0], [287.0, 650.0], [292.0, 690.0], [287.0, 668.0], [305.0, 736.0], [304.0, 689.0], [296.0, 616.0], [287.0, 568.0], [271.0, 533.0], [262.0, 528.0]], "interior": []}}, {"description": "", "bitmap": null, "tags": [], "classTitle": "periostealreaction", "points": {"exterior": [[361.0, 538.0], [366.0, 673.0], [376.0, 536.0], [369.0, 532.0]], "interior": []}}], "size": {"height": 784, "width": 613}}