{"tags": [{"name": "ao_classification", "value": "23r-M/3.1; 23u-E/7"}, "osteopenia", "projection_lat", "side_right"], "description": "", "objects": [{"description": "", "bitmap": null, "tags": [], "classTitle": "text", "points": {"exterior": [[425.0, 65.0], [479.0, 141.0]], "interior": []}}, {"description": "", "bitmap": null, "tags": [], "classTitle": "fracture", "points": {"exterior": [[186.0, 489.0], [300.0, 584.0]], "interior": []}}, {"description": "", "bitmap": null, "tags": [], "classTitle": "axis", "points": {"exterior": [[312.0, 997.0], [256.0, 69.0]], "interior": []}}, {"description": "", "bitmap": null, "tags": [], "classTitle": "periostealreaction", "points": {"exterior": [[278.0, 746.0], [278.0, 669.0], [283.0, 610.0], [285.0, 571.0], [289.0, 546.0], [293.0, 537.0], [295.0, 527.0], [276.0, 546.0], [271.0, 550.0], [272.0, 669.0]], "interior": []}}], "size": {"height": 1042, "width": 498}}