{"tags": [{"name": "ao_classification", "value": "23r-M/2.1"}, "initial_exam", "projection_ap", "side_left"], "description": "", "objects": [{"description": "", "bitmap": null, "tags": [], "classTitle": "text", "points": {"exterior": [[12.807046890258789, 406.0716972351074], [68.17422294616699, 473.7853584289551]], "interior": []}}, {"description": "", "bitmap": null, "tags": [], "classTitle": "fracture", "points": {"exterior": [[231.0, 534.0], [367.0, 599.0]], "interior": []}}, {"description": "", "bitmap": null, "tags": [], "classTitle": "axis", "points": {"exterior": [[234.0, 1072.0], [233.0, 43.0]], "interior": []}}], "size": {"height": 1078, "width": 515}}