{"tags": [{"name": "ao_classification", "value": "23-M/3.1"}, "osteopenia", "projection_lat", "side_left"], "description": "", "objects": [{"description": "", "bitmap": null, "tags": [], "classTitle": "text", "points": {"exterior": [[9.0, 385.0], [69.0, 502.0]], "interior": []}}, {"description": "", "bitmap": null, "tags": [], "classTitle": "fracture", "points": {"exterior": [[183.0, 393.0], [312.0, 482.0]], "interior": []}}, {"description": "", "bitmap": null, "tags": [], "classTitle": "axis", "points": {"exterior": [[246.0, 963.0], [263.0, 25.0]], "interior": []}}], "size": {"height": 970, "width": 499}}